sphinx_llms_txt/__init__.py
sphinx_llms_txt/collector.py
sphinx_llms_txt/manager.py
sphinx_llms_txt/processor.py
sphinx_llms_txt/writer.py
sphinx_llms_txt_jampy-0.2.2.dist-info/licenses/LICENSE
sphinx_llms_txt_jampy-0.2.2.dist-info/METADATA
sphinx_llms_txt_jampy-0.2.2.dist-info/WHEEL
sphinx_llms_txt_jampy-0.2.2.dist-info/top_level.txt
sphinx_llms_txt_jampy-0.2.2.dist-info/RECORD
